{
    "dataset": "filtered",
    "output_dir": "baseline",
    "word_embed": "bert",
    "encoder": "gru",
    "pooling": "max",
    "bidirectional": true,
    "save_best_model": true,
    "viz_projection": true,
    "class_weight": "uniform",
    "loss": "cross_entropy",
    "n_heads": 1,
    "n_layers": 3,
    "n_epochs": 15,
    "batch_size": 8,
    "seed": 14298463,
    "exclude_cls_before": false,
    "exclude_cls_after": false,
    "freeze_embedding": false,
    "normalize_logits": false,
    "device": "cuda",
    "scenario_dir": "experiments/baseline_bert_14298463/filtered/gru/uniform/cross_entropy/max/3/1/bidirectional",
    "best_epoch": 4,
    "best_val_f1": 0.7813282289599154,
    "best_val_acc": 0.7863247863247863,
    "train_started_at": "2025-03-06 23:48:53.483471",
    "train_finished_at": "2025-03-06 23:49:34.700205",
    "train_duration": "41.216734 seconds",
    "eval_started_at": "2025-03-06 23:49:35.021105",
    "eval_finished_at": "2025-03-06 23:49:35.262372",
    "eval_duration": "0.241267 seconds"
}