{
    "dataset": "filtered",
    "output_dir": "multitask",
    "word_embed": "vector-max",
    "encoder": "gru",
    "pooling": "avg",
    "bidirectional": false,
    "save_best_model": false,
    "viz_projection": true,
    "class_weight": "uniform",
    "decoding": "forward",
    "label_schema": "110",
    "loss": "multitask",
    "n_heads": 1,
    "n_layers": 3,
    "n_epochs": 15,
    "batch_size": 8,
    "seed": 82511865,
    "alpha": 1,
    "beta": 1,
    "exclude_cls_before": false,
    "exclude_cls_after": false,
    "freeze_embedding": false,
    "normalize_logits": false,
    "device": "cuda",
    "scenario_dir": "experiments/multitask_vector-max_82511865/filtered/gru/uniform/multitask/avg/3/1/unidirectional/110_forward",
    "best_epoch": 7,
    "best_val_acc": 0.6495726495726496,
    "best_val_f1": 0.5485925821598694,
    "train_started_at": "2025-03-11 17:26:40.437282",
    "train_finished_at": "2025-03-11 17:27:26.415818",
    "train_duration": "45.978536 seconds",
    "eval_started_at": "2025-03-11 17:27:27.013062",
    "eval_finished_at": "2025-03-11 17:27:27.270365",
    "eval_duration": "0.257303 seconds"
}