{
    "dataset": "filtered",
    "output_dir": "baseline",
    "word_embed": "ordinal-severity",
    "encoder": "lstm",
    "pooling": "avg",
    "bidirectional": true,
    "save_best_model": true,
    "viz_projection": true,
    "class_weight": "uniform",
    "loss": "cross_entropy",
    "n_heads": 1,
    "n_layers": 3,
    "n_epochs": 15,
    "batch_size": 8,
    "seed": 30288239,
    "exclude_cls_before": false,
    "exclude_cls_after": false,
    "freeze_embedding": false,
    "normalize_logits": false,
    "device": "cuda",
    "scenario_dir": "experiments/baseline_ordinal-severity_30288239/filtered/lstm/uniform/cross_entropy/avg/3/1/bidirectional",
    "best_epoch": 2,
    "best_val_f1": 0.8206955491899878,
    "best_val_acc": 0.8290598290598291,
    "train_started_at": "2025-03-09 16:35:44.456166",
    "train_finished_at": "2025-03-09 16:36:28.472171",
    "train_duration": "44.016005 seconds",
    "eval_started_at": "2025-03-09 16:36:28.816629",
    "eval_finished_at": "2025-03-09 16:36:29.157371",
    "eval_duration": "0.340742 seconds"
}