{
    "dataset": "filtered",
    "output_dir": "multitask",
    "word_embed": "drone-severity",
    "encoder": "lstm",
    "pooling": "last",
    "bidirectional": true,
    "save_best_model": false,
    "viz_projection": true,
    "class_weight": "uniform",
    "decoding": "backward",
    "label_schema": "0101",
    "loss": "logloss",
    "n_heads": 1,
    "n_layers": 3,
    "n_epochs": 15,
    "batch_size": 8,
    "seed": 82511865,
    "alpha": 1,
    "beta": 1,
    "exclude_cls_before": false,
    "exclude_cls_after": false,
    "freeze_embedding": false,
    "normalize_logits": false,
    "device": "cuda",
    "scenario_dir": "experiments/multitask_drone-severity_82511865/filtered/lstm/uniform/logloss/last/3/1/bidirectional/0101_backward",
    "best_epoch": 9,
    "best_val_acc": 0.8205128205128205,
    "best_val_f1": 0.825301879636245,
    "train_started_at": "2025-03-10 15:14:12.866687",
    "train_finished_at": "2025-03-10 15:14:57.889762",
    "train_duration": "45.023075 seconds",
    "eval_started_at": "2025-03-10 15:14:58.235979",
    "eval_finished_at": "2025-03-10 15:14:58.585095",
    "eval_duration": "0.349116 seconds"
}