{
    "dataset": "filtered",
    "output_dir": "multitask",
    "word_embed": "drone-severity",
    "encoder": "lstm",
    "pooling": "last",
    "bidirectional": true,
    "save_best_model": false,
    "viz_projection": true,
    "class_weight": "uniform",
    "decoding": "forward",
    "label_schema": "110",
    "loss": "logloss",
    "n_heads": 1,
    "n_layers": 3,
    "n_epochs": 15,
    "batch_size": 8,
    "seed": 246773155,
    "alpha": 1,
    "beta": 1,
    "exclude_cls_before": false,
    "exclude_cls_after": false,
    "freeze_embedding": false,
    "normalize_logits": false,
    "device": "cuda",
    "scenario_dir": "experiments/multitask_drone-severity_246773155/filtered/lstm/uniform/logloss/last/3/1/bidirectional/110_forward",
    "best_epoch": 2,
    "best_val_acc": 0.6410256410256411,
    "best_val_f1": 0.5404944586530264,
    "train_started_at": "2025-03-10 15:30:21.602495",
    "train_finished_at": "2025-03-10 15:31:06.654150",
    "train_duration": "45.051655 seconds",
    "eval_started_at": "2025-03-10 15:31:07.011712",
    "eval_finished_at": "2025-03-10 15:31:07.362227",
    "eval_duration": "0.350515 seconds"
}