{
    "dataset": "filtered",
    "output_dir": "multitask",
    "word_embed": "drone-severity",
    "encoder": "gru",
    "pooling": "avg",
    "bidirectional": false,
    "save_best_model": false,
    "viz_projection": true,
    "class_weight": "uniform",
    "decoding": "forward",
    "label_schema": "110",
    "loss": "logloss",
    "n_heads": 1,
    "n_layers": 3,
    "n_epochs": 15,
    "batch_size": 8,
    "seed": 90995999,
    "alpha": 1,
    "beta": 1,
    "exclude_cls_before": false,
    "exclude_cls_after": false,
    "freeze_embedding": false,
    "normalize_logits": false,
    "device": "cuda",
    "scenario_dir": "experiments/multitask_drone-severity_90995999/filtered/gru/uniform/logloss/avg/3/1/unidirectional/110_forward",
    "best_epoch": 6,
    "best_val_acc": 0.6495726495726496,
    "best_val_f1": 0.5507978611426887,
    "train_started_at": "2025-03-10 19:16:03.729676",
    "train_finished_at": "2025-03-10 19:16:49.278202",
    "train_duration": "45.548526 seconds",
    "eval_started_at": "2025-03-10 19:16:49.628239",
    "eval_finished_at": "2025-03-10 19:16:49.972932",
    "eval_duration": "0.344693 seconds"
}