{
    "dataset": "unfiltered",
    "output_dir": "baseline",
    "word_embed": "bert",
    "encoder": "gru",
    "pooling": "avg",
    "bidirectional": true,
    "save_best_model": true,
    "viz_projection": true,
    "class_weight": "uniform",
    "loss": "focal",
    "n_heads": 1,
    "n_layers": 3,
    "n_epochs": 15,
    "batch_size": 8,
    "seed": 30288239,
    "exclude_cls_before": false,
    "exclude_cls_after": false,
    "freeze_embedding": false,
    "normalize_logits": false,
    "device": "cuda",
    "scenario_dir": "experiments/baseline_bert_30288239/unfiltered/gru/uniform/focal/avg/3/1/bidirectional",
    "best_epoch": 6,
    "best_val_f1": 0.9544161449289599,
    "best_val_acc": 0.9553571428571429,
    "train_started_at": "2025-07-10 12:39:28.145698",
    "train_finished_at": "2025-07-10 12:41:22.328501",
    "train_duration": "114.182803 seconds",
    "eval_started_at": "2025-07-10 12:41:22.685405",
    "eval_finished_at": "2025-07-10 12:41:23.238149",
    "eval_duration": "0.552744 seconds"
}