{
    "dataset": "filtered",
    "output_dir": "multitask",
    "word_embed": "bert",
    "encoder": "none",
    "pooling": "max",
    "bidirectional": false,
    "save_best_model": false,
    "viz_projection": true,
    "class_weight": "uniform",
    "decoding": "forward",
    "label_schema": "110",
    "loss": "logloss",
    "n_heads": 1,
    "n_layers": 1,
    "n_epochs": 15,
    "batch_size": 8,
    "seed": 30288239,
    "alpha": 1,
    "beta": 1,
    "exclude_cls_before": false,
    "exclude_cls_after": false,
    "freeze_embedding": false,
    "normalize_logits": false,
    "device": "cuda",
    "scenario_dir": "experiments/multitask_bert_30288239/filtered/none/uniform/logloss/max/1/1/unidirectional/110_forward",
    "best_epoch": 2,
    "best_val_acc": 0.6666666666666666,
    "best_val_f1": 0.5996122771913254,
    "train_started_at": "2025-03-10 11:50:04.189254",
    "train_finished_at": "2025-03-10 11:50:38.875042",
    "train_duration": "34.685788 seconds",
    "eval_started_at": "2025-03-10 11:50:39.172757",
    "eval_finished_at": "2025-03-10 11:50:39.377397",
    "eval_duration": "0.20464 seconds"
}