{
    "dataset": "filtered",
    "output_dir": "fix-pooling",
    "word_embed": "drone-severity",
    "encoder": "lstm",
    "pooling": "avg",
    "bidirectional": false,
    "save_best_model": false,
    "viz_projection": true,
    "class_weight": "uniform",
    "decoding": "backward",
    "label_schema": "1111",
    "loss": "logloss",
    "n_heads": 1,
    "n_layers": 3,
    "n_epochs": 15,
    "batch_size": 8,
    "seed": 246773155,
    "alpha": 1,
    "beta": 1,
    "exclude_cls_before": false,
    "exclude_cls_after": false,
    "freeze_embedding": false,
    "normalize_logits": false,
    "device": "cuda",
    "scenario_dir": "experiments/fix-pooling_drone-severity_246773155/filtered/lstm/uniform/logloss/avg/3/1/unidirectional/1111_backward",
    "best_epoch": 4,
    "best_val_acc": 0.8547008547008547,
    "best_val_f1": 0.8542048744477894,
    "train_started_at": "2025-06-22 03:46:44.719535",
    "train_finished_at": "2025-06-22 03:47:17.765814",
    "train_duration": "33.046279 seconds",
    "eval_started_at": "2025-06-22 03:47:18.161816",
    "eval_finished_at": "2025-06-22 03:47:18.397608",
    "eval_duration": "0.235792 seconds"
}