{
    "dataset": "filtered",
    "output_dir": "multitask",
    "word_embed": "drone-severity",
    "encoder": "none",
    "pooling": "max",
    "bidirectional": false,
    "save_best_model": false,
    "viz_projection": true,
    "class_weight": "uniform",
    "decoding": "backward",
    "label_schema": "0111",
    "loss": "multitask",
    "n_heads": 1,
    "n_layers": 1,
    "n_epochs": 15,
    "batch_size": 8,
    "seed": 82511865,
    "alpha": 1,
    "beta": 1,
    "exclude_cls_before": false,
    "exclude_cls_after": false,
    "freeze_embedding": false,
    "normalize_logits": false,
    "device": "cuda",
    "scenario_dir": "experiments/multitask_drone-severity_82511865/filtered/none/uniform/multitask/max/1/1/unidirectional/0111_backward",
    "best_epoch": 4,
    "best_val_acc": 0.8290598290598291,
    "best_val_f1": 0.8259280855416499,
    "train_started_at": "2025-03-08 09:05:12.728374",
    "train_finished_at": "2025-03-08 09:05:49.666175",
    "train_duration": "36.937801 seconds",
    "eval_started_at": "2025-03-08 09:05:50.199623",
    "eval_finished_at": "2025-03-08 09:05:50.411107",
    "eval_duration": "0.211484 seconds"
}